libaio/__init__.py
libaio/libaio.so
libaio/libaio.so.1
libaio/libaio.so.1.0.1
libaio_bins-0.0.1.dist-info/METADATA
libaio_bins-0.0.1.dist-info/WHEEL
libaio_bins-0.0.1.dist-info/top_level.txt
libaio_bins-0.0.1.dist-info/RECORD
